fastapi_basic_auth/__init__.py
fastapi_basic_auth/main.py
fastapi_basic_auth/schema.py
fastapi_basic_auth-0.1.5.dist-info/METADATA
fastapi_basic_auth-0.1.5.dist-info/WHEEL
fastapi_basic_auth-0.1.5.dist-info/RECORD
