Metadata-Version: 2.1
Name: fastapi-basic-auth
Version: 0.1.5
Summary: A simple and flexible Basic Authentication middleware for FastAPI applications
Home-page: https://github.com/dakohhh/fastapi-basic-auth
License: MIT
Keywords: fastapi,authentication,basic-auth,middleware
Author: dakohhh
Author-email: wiizzydreadmill@gmail.com
Requires-Python: >=3.9,<4.0
Classifier: Development Status :: 4 - Beta
Classifier: Framework :: FastAPI
Classifier: Intended Audience :: Developers
Classifier: License :: OSI Approved :: MIT License
Classifier: Programming Language :: Python :: 3
Classifier: Programming Language :: Python :: 3.9
Classifier: Programming Language :: Python :: 3.10
Classifier: Programming Language :: Python :: 3.11
Classifier: Programming Language :: Python :: 3.12
Requires-Dist: fastapi (>=0.115.7,<0.116.0)
Requires-Dist: httpx (>=0.28.1,<0.29.0)
Requires-Dist: pydantic (>=2.10.6,<3.0.0)
Project-URL: Repository, https://github.com/dakohhh/fastapi-basic-auth
